pygrpm/__init__.py
pygrpm/brachy_dvh/__init__.py
pygrpm/brachy_dvh/calculate.py
pygrpm/brachy_dvh/contour.py
pygrpm/brachy_dvh/dicom/__init__.py
pygrpm/brachy_dvh/dicom/brachy_rt_plan_wrapper.py
pygrpm/brachy_dvh/dicom/exceptions.py
pygrpm/brachy_dvh/dicom/rt_struct_wrapper.py
pygrpm/brachy_dvh/dose_calculation_service.py
pygrpm/brachy_dvh/dose_calculation_service_from_dicom.py
pygrpm/brachy_dvh/dose_parameters.py
pygrpm/brachy_dvh/dvh.py
pygrpm/brachy_dvh/source_position.py
pygrpm/brachy_dvh/structure.py
pygrpm/brachy_dvh/utils.py
pygrpm/dicom/__init__.py
pygrpm/dicom/reader.py
pygrpm/dicom/sr/__init__.py
pygrpm/dicom/sr/builder.py
pygrpm/dicom/sr/data/DCM_2023c_20230704.csv
pygrpm/dicom/sr/dicom_content_sequence.py
pygrpm/dicom/sr/sr.py
pygrpm/dicom/sr/sr_tags.py
pygrpm/dicom/sr/terminologies.py
pygrpm/dicom/sr/utils.py
pygrpm/dicom/structures.py
pygrpm/dicom/uid.py
pygrpm/dicom/utils.py
pygrpm/geometry/__init__.py
pygrpm/geometry/data/CT01_materials.json
pygrpm/geometry/egsphant.py
pygrpm/material/__init__.py
pygrpm/material/hounsfield_conversion.py
pygrpm/material/nistparser/__init__.py
pygrpm/material/nistparser/internal/__init__.py
pygrpm/material/nistparser/internal/data/material_lookup_key.json
pygrpm/material/nistparser/internal/enum_generator.py
pygrpm/material/nistparser/materials_enum.py
pygrpm/material/nistparser/nistparser.py
pygrpm/tg263/__init__.py
pygrpm/tg263/nomenclature/__init__.py
pygrpm/tg263/nomenclature/_dictionary.py
pygrpm/tg263/nomenclature/_exceptions.py
pygrpm/tg263/nomenclature/structures.py
pygrpm/tg263/nomenclature/tg263.json
pygrpm/tg43/README.md
pygrpm/tg43/__init__.py
pygrpm/tg43/data/Flexisource/F.dat
pygrpm/tg43/data/Flexisource/HalfLife.dat
pygrpm/tg43/data/Flexisource/L.dat
pygrpm/tg43/data/Flexisource/Lambda.dat
pygrpm/tg43/data/Flexisource/gL.dat
pygrpm/tg43/data/IsoAid/F.dat
pygrpm/tg43/data/IsoAid/HalfLife.dat
pygrpm/tg43/data/IsoAid/L.dat
pygrpm/tg43/data/IsoAid/Lambda.dat
pygrpm/tg43/data/IsoAid/gL.dat
pygrpm-0.8.0.dist-info/LICENSE.txt
pygrpm-0.8.0.dist-info/METADATA
pygrpm-0.8.0.dist-info/WHEEL
pygrpm-0.8.0.dist-info/RECORD
