Metadata-Version: 2.3
Name: pygrpm
Version: 0.8.0
Summary: Medical physics library containing many utilty functions
License: AGPL
Keywords: Medical physics,dicom,tg43
Author: Yannick Lemaréchal
Author-email: yannick.lemarechal.1@ulaval.ca
Maintainer: Yannick Lemaréchal
Maintainer-email: yannick.lemarechal.1@ulaval.ca
Requires-Python: >=3.9,<4.0
Classifier: License :: Other/Proprietary License
Classifier: Programming Language :: Python :: 3
Classifier: Programming Language :: Python :: 3.9
Classifier: Programming Language :: Python :: 3.10
Classifier: Programming Language :: Python :: 3.11
Classifier: Programming Language :: Python :: 3.12
Classifier: Programming Language :: Python :: 3.13
Provides-Extra: all
Provides-Extra: matplotlib
Provides-Extra: pandas
Provides-Extra: periodictable
Provides-Extra: scikit-image
Provides-Extra: scipy
Provides-Extra: trimesh
Provides-Extra: xarray
Requires-Dist: dicompyler-core (>=0.5.3,<0.6.0)
Requires-Dist: matplotlib (>=3.5.0,<4.0.0) ; extra == "matplotlib" or extra == "all"
Requires-Dist: numpy (>=1.23.0,<2.0.0)
Requires-Dist: pandas (>=1.4.0) ; extra == "pandas" or extra == "all"
Requires-Dist: periodictable (==2.0.0) ; extra == "periodictable" or extra == "all"
Requires-Dist: pydantic (>=1.10.0,<2.0.0)
Requires-Dist: pydicom (>=2.2.2,<3.0.0)
Requires-Dist: scikit-image (>=0.21.0,<0.22.0) ; extra == "scikit-image" or extra == "all"
Requires-Dist: scipy (>=1.9.0) ; extra == "scipy" or extra == "all"
Requires-Dist: trimesh (>=4.6.12,<5.0.0) ; extra == "trimesh" or extra == "all"
Requires-Dist: xarray (>=2022.6.0) ; extra == "xarray" or extra == "all"
Project-URL: Homepage, https://paradim.science/
Project-URL: Repository, https://git.valeria.science/YALEM10/pygrpm
